{"ignored": [], "strvaluetransfrmr": [], "idx": 49, "transition": {"cookies": [["punchh", "deleted"], ["punchh", "deleted"]], "response_headers": [["Date", "Fri, 29 Sep 2017 22:21:44 GMT"], ["Server", "Apache/2.4.18 (Ubuntu)"], ["Expires", "Thu, 19 Nov 1981 08:52:00 GMT"], ["Cache-Control", "no-store, no-cache, must-revalidate"], ["Pragma", "no-cache"], ["Vary", "Accept-Encoding"], ["Content-Type", "text/html; charset=UTF-8"], ["Content-Length", "3359"]], "idx": 60, "url": "https://www.schlotzskys.com/find-your-schlotzskys/", "request_headers": [["Host", "www.schlotzskys.com"], ["User-Agent", "Mozilla/5.0 (X11; Linux x86_64; rv:47.0) Gecko/20100101 Firefox/47.0"], ["Accept", "*/*"], ["Accept-Language", "en-US,en;q=0.5"], ["Accept-Encoding", "gzip, deflate, br"], ["Content-Type", "application/x-www-form-urlencoded; charset=UTF-8"], ["X-Requested-With", "XMLHttpRequest"], ["Referer", "https://www.schlotzskys.com/find-your-schlotzskys/"], ["Content-Length", "24"], ["Connection", "keep-alive"]], "content": "\t\t\t\t\n\t\t\t\t\t\t\t\t\t<div class=\"each-result\" id=\"location-1\">\n\t\t\t\t\t\t<div class=\"results-top\">\n\t\t\t\t\t\t\t\n\t\t\t\t\t\t\t<div class=\"resultscol col-md-1\">\n\t\t\t\t\t\t\t\t<div class=\"search-results-key-new\">\n\t\t\t\t\t\t\t\t\t1\t\n\t\t\t\t\t\t\t\t</div>\n\t\t\t\t\t\t\t</div>\n\t\t\t\t\t\t\t<div class=\"resultscol col-md-5\">\n\t\t\t\t\t\t\t\t\n\t\t\t\t\t\t\t\t<div class=\"search-results-address1\">10120 SE 256th Street</div>\n\t\t\t\t\t\t\t\t\t\t\t\t\t\t\t\t<div class=\"search-results-city-state-zip\">Kent, WA 98030</div>\n\t\t\t\t\t\t\t\t\n\t\t\t\t\t\t\t\t<div class=\"fixed-items\">\n\t\t\t\t\t\t\t\t\n\t\t\t\t\t\t\t\t\t\n\t\t\t\t\t\t\t\t\n\t\t\t\t\t\t\t\t\t\t\t\t\t\t\t\t\t\t\t<span>Call For Catering: <a href=\"tel:1-855-335-4837\">\n\t\t\t\t\t\t\t\t\t\t\t855-DELIVER (855-335-4837)\n\t\t\t\t\t\t\t\t\t\t</a> </span> <br/>\n\t\t\t\t\t\t\t\t\t\t\t\t\t\t\t\t\t\n\t\t\n\t\t\t\t\t\t\t\t\t\n\t\t\t\t\t\t\t\t\t<a href=\"https://www.schlotzskys.com/find-your-schlotzskys/washington/kent/6455/\" >Location Info</a> |\n\t\t\t\t\t\t\t\t\t\n\t\t\t\t\t\t\t\t\t<a href=\"/menu/\">Menu</a>\n\t\t\t\t\t\t\t\t\t\n\t\t\t\t\t\t\t\t\t\t\t\t\t\t\t\t\t\t\n\t\t\t\t\t\t\t\t\t\t\t\t\t\t\t\t\t\t\t| <a href=\"https://ordering.schlotzskys.com/index.cfm?fuseaction=order&amp;action=preorder&amp;store_code=6455\" target=\"_blank\">Order Catering</a>\n\t\t\t\t\t\t\t\t\t\n\n\t\t\t\t\t\t\t\t\t\t\t\t\t\t\t\t\t</div>\n\t\t\t\t\t\t\t\t\n\t\t\t\t\t\t\t</div>\n\n\t\t\t\t\t\t\t<span class=\"hidden-xs hidden-sm col-md-6\">\n\t\t\t\t\t\t\t\t<div class=\"check-col resultscol\">\n\t\t\t\t\t\t\t\t\t\t\t\t\t\t\t\t\t\t\t&nbsp;\n\t\t\t\t\t\t\t\t\t\t\t\t\t\t\t\t\t</div>\n\t\t\t\t\t\t\t\t<div class=\"check-col resultscol\">\n\t\t\t\t\t\t\t\t\t\t\t\t\t\t\t\t\t\t\t<i class=\"fa fa-circle-o \"></i>\n\t\t\t\t\t\t\t\t\t\t\t\t\t\t\t\t\t</div>\n\t\t\t\t\t\t\t\t<div class=\"check-col resultscol\">\n\t\t\t\t\t\t\t\t\t\t\t\t\t\t\t\t\t\t\t&nbsp;\n\t\t\t\t\t\t\t\t\t\t\t\t\t\t\t\t\t</div>\n\t\t\t\t\t\t\t\t<div class=\"check-col resultscol\">\n\t\t\t\t\t\t\t\t\t\t\t\t\t\t\t\t\t\t\t<i class=\"fa fa-circle-o \"></i>\n\t\t\t\t\t\t\t\t\t\t\t\t\t\t\t\t\t</div>\n\t\t\t\t\t\t\t\t<div class=\"check-col resultscol\">\n\t\t\t\t\t\t\t\t\t\t\t\t\t\t\t\t\t\t\t<i class=\"fa fa-circle-o \"></i>\n\t\t\t\t\t\t\t\t\t\t\t\t\t\t\t\t\t</div>\n\t\t\t\t\t\t\t\t<div class=\"check-col resultscol\">\n\t\t\t\t\t\t\t\t\t\t\t\t\t\t\t\t\t\t\t<i class=\"fa fa-circle-o \"></i>\n\t\t\t\t\t\t\t\t\t\t\t\t\t\t\t\t\t</div>\n\t\t\t\t\t\t\t\t<div class=\"check-col resultscol\">\n\t\t\t\t\t\t\t\t\t\t\t\t\t\t\t\t\t\t\t&nbsp;\n\t\t\t\t\t\t\t\t\t\t\t\t\t\t\t\t\t</div>\n\t\t\t\t\t\t\t\t<div class=\"check-col resultscol\">\n\t\t\t\t\t\t\t\t\t\t\t\t\t\t\t\t\t\t\t&nbsp;\n\t\t\t\t\t\t\t\t\t\t\t\t\t\t\t\t\t</div>\n\t\t\t\t\t\t\t\t<div class=\"check-col resultscol\">\n\t\t\t\t\t\t\t\t\t\t\t\t\t\t\t\t\t\t\t<i class=\"fa fa-circle-o \"></i>\n\t\t\t\t\t\t\t\t\t\t\t\t\t\t\t\t\t\t\t<!-- &nbsp; -->\n\t\t\t\t\t\t\t\t\t\t\t\t\t\t\t\t\t</div>\n\t\t\t\t\t\t\t</span>\n\t\t\t\t\t\t\n\t\t\t\t\t\t</div>\n\t\t\t\t\t</div>\n\t\t\t\t\t\t\t\t\t<script type=\"text/javascript\">\n\t\t\t\t\t$(document).ready(function() {\n\t\t\t\t\t\tvar map;\n\t\t\t\t\t\tmap = new GMaps({\n\t\t\t\t\t\t\tdiv: '#findMap',\n\t\t\t\t\t\t\tlat: 47.6021,\n\t\t\t\t\t\t\tlng: -122.3284,\n\t\t\t\t\t\t\tremoveMarkers:true,\n\t\t\t\t\t\t\tzoom:10\n\t\t\t\t\t\t});\n\n\t\t\t\t\t\t var mapIco = {\n\t\t\t\t\t\t    url: '/public/images/mapicon.png',\n\t\t\t\t\t\t    // This marker is 20 pixels wide by 32 pixels tall.\n\t\t\t\t\t\t    size: new google.maps.Size(35, 51),\n\t\t\t\t\t\t    // The origin for this image is 0,0.\n\t\t\t\t\t\t    origin: new google.maps.Point(0,0),\n\t\t\t\t\t\t    // The anchor for this image is the base of the flagpole at 0,32.\n\t\t\t\t\t\t    anchor: new google.maps.Point(0, 25.5)\n\t\t\t\t\t\t  };\n\t\t\n\t\t\t\t\t\t\t\t\t\t\t\tmap.addMarker({\n\t\t\t\t\t\t\tlat: 47.3725133,\n\t\t\t\t\t\t\tlng: -122.2049702,\n\t\t\t\t\t\t\ticon: mapIco,\n\t\t\t\t\t\t\ttitle: \"Schlotzsky's\",\n\t\t\t\t\t\t\t\tclick: function(e) {\n\t\t\t\t\t\t\t\t\t$('.each-result.active').removeClass('active');\n\t\t\t\t\t\t\t\t\t$('#location-1').addClass('active');\n\t\t\t\t\t\t\t\t\t$('.search-results').scrollTo('#location-1',500);\n\t\t\t\t\t\t\t\t}\n\t\t\t\t\t\t});\n\t\t\t\t\t\tmap.drawOverlay({\n\t\t\t\t\t\t\tlat: 47.3725133,\n\t\t\t\t\t\t\tlng: -122.2049702,\n\t\t\t\t\t\t\tlayer:'floatPane',\n\t\t\t\t\t\t\tcontent: '<div class=\"maps-number\">1</div>'\n\t\t\t\t\t\t});\n\t\t\t\t\t\t\t\t\t\t\t\n\t\t\t\t\t});\n\t\t\t\t</script>\n\t\t\t\t", "verb": "POST", "SERIALISED_CLASS_NAME": "Transition", "content_type": "text/html; charset=UTF-8", "data": [["search[search]", "98104"]], "post_data_type": "post"}, "selector": [], "SERIALISED_CLASS_NAME": "Model", "override": [{"param_name": "search[search]", "model": {"param_name": "LOCATION", "strvaluetransfrmr": {"SERIALISED_CLASS_NAME": "StrValueNullTransformer"}, "idx": 48, "SERIALISED_CLASS_NAME": "SimpleValueModel"}, "param_type": "POST"}], "columns": [{"param_name": "street_address_raw", "sel": {"text_idx": 0, "prefix": "", "node_sel_mode": 0, "SERIALISED_CLASS_NAME": "XPathSelector", "path": "//div/div[@class='results-top']/div[@class='resultscol col-md-5']/div[@class='search-results-address1']", "suffix": "", "external": false}, "valtransform": {"SERIALISED_CLASS_NAME": "StrValueNullTransformer"}}, {"param_name": "location_raw", "sel": {"text_idx": 0, "prefix": "", "node_sel_mode": 0, "SERIALISED_CLASS_NAME": "XPathSelector", "path": "//div/div[@class='results-top']/div[@class='resultscol col-md-5']/div[@class='search-results-city-state-zip']", "suffix": "", "external": false}, "valtransform": {"SERIALISED_CLASS_NAME": "StrValueNullTransformer"}}]}